{
  "id": "gongwei4",
  "displayName": "gongwei4",
  "description": "YOLO11m ONNX horizontal bounding-box detection model trained on the gongwei4 dataset (640 input, 5 classes).",
  "taskType": "detection",
  "modelFile": "best.onnx",
  "inputWidth": 640,
  "inputHeight": 640,
  "classes": [
    "QR",
    "Plugging",
    "Nozzling",
    "MovingLabel",
    "Done"
  ],
  "boxColors": [
    "#29B6F6",
    "#66BB6A",
    "#FFA726",
    "#EF5350",
    "#AB47BC"
  ],
  "boxThickness": 2,
  "labelFontScale": 0.9,
  "yolo": {
    "outputLayout": "channels_first",
    "scoreMode": "class_only",
    "classCount": 5
  }
}